[
  {
    "ContainingType": "ThAmCo.Events.Controllers.EventsController",
    "Method": "GetEvents",
    "RelativePath": "api/Events",
    "HttpMethod": "GET",
    "IsController": true,
    "Order": 0,
    "Parameters": [],
    "ReturnTypes": [
      {
        "Type": "System.Collections.Generic.IEnumerable\u00601[[ThAmCo.Events.DTOs.EventDTO, ThAmCo.Events, Version=1.0.0.0, Culture=neutral, PublicKeyToken=null]]",
        "MediaTypes": [
          "text/plain",
          "application/json",
          "text/json"
        ],
        "StatusCode": 200
      }
    ]
  },
  {
    "ContainingType": "ThAmCo.Events.Controllers.EventsController",
    "Method": "CreateEvent",
    "RelativePath": "api/Events",
    "HttpMethod": "POST",
    "IsController": true,
    "Order": 0,
    "Parameters": [
      {
        "Name": "dto",
        "Type": "ThAmCo.Events.DTOs.EventDTO",
        "IsRequired": true
      }
    ],
    "ReturnTypes": [
      {
        "Type": "ThAmCo.Events.DTOs.EventDTO",
        "MediaTypes": [
          "text/plain",
          "application/json",
          "text/json"
        ],
        "StatusCode": 200
      }
    ]
  },
  {
    "ContainingType": "ThAmCo.Events.Controllers.EventsController",
    "Method": "GetEvent",
    "RelativePath": "api/Events/{id}",
    "HttpMethod": "GET",
    "IsController": true,
    "Order": 0,
    "Parameters": [
      {
        "Name": "id",
        "Type": "System.Int32",
        "IsRequired": true
      }
    ],
    "ReturnTypes": [
      {
        "Type": "ThAmCo.Events.DTOs.EventDTO",
        "MediaTypes": [
          "text/plain",
          "application/json",
          "text/json"
        ],
        "StatusCode": 200
      }
    ]
  },
  {
    "ContainingType": "ThAmCo.Events.Controllers.EventsController",
    "Method": "UpdateEvent",
    "RelativePath": "api/Events/{id}",
    "HttpMethod": "PUT",
    "IsController": true,
    "Order": 0,
    "Parameters": [
      {
        "Name": "id",
        "Type": "System.Int32",
        "IsRequired": true
      },
      {
        "Name": "dto",
        "Type": "ThAmCo.Events.DTOs.EventDTO",
        "IsRequired": true
      }
    ],
    "ReturnTypes": []
  },
  {
    "ContainingType": "ThAmCo.Events.Controllers.EventsController",
    "Method": "DeleteEvent",
    "RelativePath": "api/Events/{id}",
    "HttpMethod": "DELETE",
    "IsController": true,
    "Order": 0,
    "Parameters": [
      {
        "Name": "id",
        "Type": "System.Int32",
        "IsRequired": true
      }
    ],
    "ReturnTypes": []
  },
  {
    "ContainingType": "ThAmCo.Events.Controllers.GuestBookingsController",
    "Method": "GetGuestBookings",
    "RelativePath": "api/GuestBookings",
    "HttpMethod": "GET",
    "IsController": true,
    "Order": 0,
    "Parameters": [],
    "ReturnTypes": [
      {
        "Type": "System.Collections.Generic.IEnumerable\u00601[[ThAmCo.Events.DTOs.GuestBookingDTO, ThAmCo.Events, Version=1.0.0.0, Culture=neutral, PublicKeyToken=null]]",
        "MediaTypes": [
          "text/plain",
          "application/json",
          "text/json"
        ],
        "StatusCode": 200
      }
    ]
  },
  {
    "ContainingType": "ThAmCo.Events.Controllers.GuestBookingsController",
    "Method": "CreateGuestBooking",
    "RelativePath": "api/GuestBookings",
    "HttpMethod": "POST",
    "IsController": true,
    "Order": 0,
    "Parameters": [
      {
        "Name": "dto",
        "Type": "ThAmCo.Events.DTOs.GuestBookingDTO",
        "IsRequired": true
      }
    ],
    "ReturnTypes": [
      {
        "Type": "ThAmCo.Events.DTOs.GuestBookingDTO",
        "MediaTypes": [
          "text/plain",
          "application/json",
          "text/json"
        ],
        "StatusCode": 200
      }
    ]
  },
  {
    "ContainingType": "ThAmCo.Events.Controllers.GuestBookingsController",
    "Method": "GetGuestBooking",
    "RelativePath": "api/GuestBookings/{eventId}/{guestId}",
    "HttpMethod": "GET",
    "IsController": true,
    "Order": 0,
    "Parameters": [
      {
        "Name": "eventId",
        "Type": "System.Int32",
        "IsRequired": true
      },
      {
        "Name": "guestId",
        "Type": "System.Int32",
        "IsRequired": true
      }
    ],
    "ReturnTypes": [
      {
        "Type": "ThAmCo.Events.DTOs.GuestBookingDTO",
        "MediaTypes": [
          "text/plain",
          "application/json",
          "text/json"
        ],
        "StatusCode": 200
      }
    ]
  },
  {
    "ContainingType": "ThAmCo.Events.Controllers.GuestBookingsController",
    "Method": "UpdateGuestBooking",
    "RelativePath": "api/GuestBookings/{eventId}/{guestId}",
    "HttpMethod": "PUT",
    "IsController": true,
    "Order": 0,
    "Parameters": [
      {
        "Name": "eventId",
        "Type": "System.Int32",
        "IsRequired": true
      },
      {
        "Name": "guestId",
        "Type": "System.Int32",
        "IsRequired": true
      },
      {
        "Name": "dto",
        "Type": "ThAmCo.Events.DTOs.GuestBookingDTO",
        "IsRequired": true
      }
    ],
    "ReturnTypes": []
  },
  {
    "ContainingType": "ThAmCo.Events.Controllers.GuestBookingsController",
    "Method": "DeleteGuestBooking",
    "RelativePath": "api/GuestBookings/{eventId}/{guestId}",
    "HttpMethod": "DELETE",
    "IsController": true,
    "Order": 0,
    "Parameters": [
      {
        "Name": "eventId",
        "Type": "System.Int32",
        "IsRequired": true
      },
      {
        "Name": "guestId",
        "Type": "System.Int32",
        "IsRequired": true
      }
    ],
    "ReturnTypes": []
  },
  {
    "ContainingType": "ThAmCo.Events.Controllers.GuestsController",
    "Method": "GetGuests",
    "RelativePath": "api/Guests",
    "HttpMethod": "GET",
    "IsController": true,
    "Order": 0,
    "Parameters": [],
    "ReturnTypes": [
      {
        "Type": "System.Collections.Generic.IEnumerable\u00601[[ThAmCo.Events.DTOs.GuestDTO, ThAmCo.Events, Version=1.0.0.0, Culture=neutral, PublicKeyToken=null]]",
        "MediaTypes": [
          "text/plain",
          "application/json",
          "text/json"
        ],
        "StatusCode": 200
      }
    ]
  },
  {
    "ContainingType": "ThAmCo.Events.Controllers.GuestsController",
    "Method": "CreateGuest",
    "RelativePath": "api/Guests",
    "HttpMethod": "POST",
    "IsController": true,
    "Order": 0,
    "Parameters": [
      {
        "Name": "dto",
        "Type": "ThAmCo.Events.DTOs.GuestDTO",
        "IsRequired": true
      }
    ],
    "ReturnTypes": [
      {
        "Type": "ThAmCo.Events.DTOs.GuestDTO",
        "MediaTypes": [
          "text/plain",
          "application/json",
          "text/json"
        ],
        "StatusCode": 200
      }
    ]
  },
  {
    "ContainingType": "ThAmCo.Events.Controllers.GuestsController",
    "Method": "GetGuest",
    "RelativePath": "api/Guests/{id}",
    "HttpMethod": "GET",
    "IsController": true,
    "Order": 0,
    "Parameters": [
      {
        "Name": "id",
        "Type": "System.Int32",
        "IsRequired": true
      }
    ],
    "ReturnTypes": [
      {
        "Type": "ThAmCo.Events.DTOs.GuestDTO",
        "MediaTypes": [
          "text/plain",
          "application/json",
          "text/json"
        ],
        "StatusCode": 200
      }
    ]
  },
  {
    "ContainingType": "ThAmCo.Events.Controllers.GuestsController",
    "Method": "UpdateGuest",
    "RelativePath": "api/Guests/{id}",
    "HttpMethod": "PUT",
    "IsController": true,
    "Order": 0,
    "Parameters": [
      {
        "Name": "id",
        "Type": "System.Int32",
        "IsRequired": true
      },
      {
        "Name": "dto",
        "Type": "ThAmCo.Events.DTOs.GuestDTO",
        "IsRequired": true
      }
    ],
    "ReturnTypes": []
  },
  {
    "ContainingType": "ThAmCo.Events.Controllers.GuestsController",
    "Method": "DeleteGuest",
    "RelativePath": "api/Guests/{id}",
    "HttpMethod": "DELETE",
    "IsController": true,
    "Order": 0,
    "Parameters": [
      {
        "Name": "id",
        "Type": "System.Int32",
        "IsRequired": true
      }
    ],
    "ReturnTypes": []
  },
  {
    "ContainingType": "ThAmCo.Events.Controllers.StaffController",
    "Method": "GetStaff",
    "RelativePath": "api/Staff",
    "HttpMethod": "GET",
    "IsController": true,
    "Order": 0,
    "Parameters": [],
    "ReturnTypes": [
      {
        "Type": "System.Collections.Generic.IEnumerable\u00601[[ThAmCo.Events.DTOs.StaffDTO, ThAmCo.Events, Version=1.0.0.0, Culture=neutral, PublicKeyToken=null]]",
        "MediaTypes": [
          "text/plain",
          "application/json",
          "text/json"
        ],
        "StatusCode": 200
      }
    ]
  },
  {
    "ContainingType": "ThAmCo.Events.Controllers.StaffController",
    "Method": "CreateStaff",
    "RelativePath": "api/Staff",
    "HttpMethod": "POST",
    "IsController": true,
    "Order": 0,
    "Parameters": [
      {
        "Name": "dto",
        "Type": "ThAmCo.Events.DTOs.StaffDTO",
        "IsRequired": true
      }
    ],
    "ReturnTypes": [
      {
        "Type": "ThAmCo.Events.DTOs.StaffDTO",
        "MediaTypes": [
          "text/plain",
          "application/json",
          "text/json"
        ],
        "StatusCode": 200
      }
    ]
  },
  {
    "ContainingType": "ThAmCo.Events.Controllers.StaffController",
    "Method": "GetStaff",
    "RelativePath": "api/Staff/{id}",
    "HttpMethod": "GET",
    "IsController": true,
    "Order": 0,
    "Parameters": [
      {
        "Name": "id",
        "Type": "System.Int32",
        "IsRequired": true
      }
    ],
    "ReturnTypes": [
      {
        "Type": "ThAmCo.Events.DTOs.StaffDTO",
        "MediaTypes": [
          "text/plain",
          "application/json",
          "text/json"
        ],
        "StatusCode": 200
      }
    ]
  },
  {
    "ContainingType": "ThAmCo.Events.Controllers.StaffController",
    "Method": "UpdateStaff",
    "RelativePath": "api/Staff/{id}",
    "HttpMethod": "PUT",
    "IsController": true,
    "Order": 0,
    "Parameters": [
      {
        "Name": "id",
        "Type": "System.Int32",
        "IsRequired": true
      },
      {
        "Name": "dto",
        "Type": "ThAmCo.Events.DTOs.StaffDTO",
        "IsRequired": true
      }
    ],
    "ReturnTypes": []
  },
  {
    "ContainingType": "ThAmCo.Events.Controllers.StaffController",
    "Method": "DeleteStaff",
    "RelativePath": "api/Staff/{id}",
    "HttpMethod": "DELETE",
    "IsController": true,
    "Order": 0,
    "Parameters": [
      {
        "Name": "id",
        "Type": "System.Int32",
        "IsRequired": true
      }
    ],
    "ReturnTypes": []
  },
  {
    "ContainingType": "ThAmCo.Events.Controllers.StaffingsController",
    "Method": "GetStaffings",
    "RelativePath": "api/Staffings",
    "HttpMethod": "GET",
    "IsController": true,
    "Order": 0,
    "Parameters": [],
    "ReturnTypes": [
      {
        "Type": "System.Collections.Generic.IEnumerable\u00601[[ThAmCo.Events.DTOs.StaffingDTO, ThAmCo.Events, Version=1.0.0.0, Culture=neutral, PublicKeyToken=null]]",
        "MediaTypes": [
          "text/plain",
          "application/json",
          "text/json"
        ],
        "StatusCode": 200
      }
    ]
  },
  {
    "ContainingType": "ThAmCo.Events.Controllers.StaffingsController",
    "Method": "CreateStaffing",
    "RelativePath": "api/Staffings",
    "HttpMethod": "POST",
    "IsController": true,
    "Order": 0,
    "Parameters": [
      {
        "Name": "dto",
        "Type": "ThAmCo.Events.DTOs.StaffingDTO",
        "IsRequired": true
      }
    ],
    "ReturnTypes": [
      {
        "Type": "ThAmCo.Events.DTOs.StaffingDTO",
        "MediaTypes": [
          "text/plain",
          "application/json",
          "text/json"
        ],
        "StatusCode": 200
      }
    ]
  },
  {
    "ContainingType": "ThAmCo.Events.Controllers.StaffingsController",
    "Method": "GetStaffing",
    "RelativePath": "api/Staffings/{staffId}/{eventId}",
    "HttpMethod": "GET",
    "IsController": true,
    "Order": 0,
    "Parameters": [
      {
        "Name": "staffId",
        "Type": "System.Int32",
        "IsRequired": true
      },
      {
        "Name": "eventId",
        "Type": "System.Int32",
        "IsRequired": true
      }
    ],
    "ReturnTypes": [
      {
        "Type": "ThAmCo.Events.DTOs.StaffingDTO",
        "MediaTypes": [
          "text/plain",
          "application/json",
          "text/json"
        ],
        "StatusCode": 200
      }
    ]
  },
  {
    "ContainingType": "ThAmCo.Events.Controllers.StaffingsController",
    "Method": "DeleteStaffing",
    "RelativePath": "api/Staffings/{staffId}/{eventId}",
    "HttpMethod": "DELETE",
    "IsController": true,
    "Order": 0,
    "Parameters": [
      {
        "Name": "staffId",
        "Type": "System.Int32",
        "IsRequired": true
      },
      {
        "Name": "eventId",
        "Type": "System.Int32",
        "IsRequired": true
      }
    ],
    "ReturnTypes": []
  }
]